mdis/__init__.py
mdis/dispatcher.py
mdis/visitor.py
mdis/walker.py
mdis-0.5.1.dist-info/LICENSE
mdis-0.5.1.dist-info/METADATA
mdis-0.5.1.dist-info/WHEEL
mdis-0.5.1.dist-info/top_level.txt
mdis-0.5.1.dist-info/RECORD
