Metadata-Version: 2.1
Name: mdis
Version: 0.5.1
Summary: Python dispatching library
Author-email: Dmitry Selyutin <ghostmansd@gmail.com>
Project-URL: Homepage, https://git.libre-soc.org/?p=mdis.git
Project-URL: Bug Tracker, https://bugs.libre-soc.org/
Keywords: dispatch,dispather,map,iterator,iterable,visitor,walker
Classifier: Development Status :: 2 - Pre-Alpha
Classifier: Intended Audience :: Developers
Classifier: Topic :: Software Development :: Libraries
Classifier: Topic :: Software Development :: Libraries :: Python Modules
Classifier: Programming Language :: Python :: 3
Classifier: Programming Language :: Python :: 3 :: Only
Classifier: License :: OSI Approved :: BSD License
Classifier: Operating System :: OS Independent
Requires-Python: >=3.0
License-File: LICENSE
